analytica/__init__.py
analytica-0.0.3.dist-info/LICENCE
analytica-0.0.3.dist-info/METADATA
analytica-0.0.3.dist-info/WHEEL
analytica-0.0.3.dist-info/top_level.txt
analytica-0.0.3.dist-info/RECORD
